getpersiann/__init__.py
getpersiann/get_data.py
getpersiann/process.py
getpersiann-0.1.3.dist-info/METADATA
getpersiann-0.1.3.dist-info/WHEEL
getpersiann-0.1.3.dist-info/entry_points.txt
getpersiann-0.1.3.dist-info/top_level.txt
getpersiann-0.1.3.dist-info/RECORD
