Metadata-Version: 2.4
Name: getpersiann
Version: 0.1.3
Summary: Download and process Persiann data
Author-email: Tomás Calvi <tcalvi@ina.gob.ar>, Juan Bianchi <jbianchi@ina.gob.ar>
License: MIT
Requires-Python: >=3.9
Requires-Dist: requests
Requires-Dist: rasterio
Requires-Dist: fiona
Requires-Dist: wheel
Requires-Dist: setuptools>=67
